MANIFEST.in
README
setup.py
django_object_log.egg-info/PKG-INFO
django_object_log.egg-info/SOURCES.txt
django_object_log.egg-info/dependency_links.txt
django_object_log.egg-info/top_level.txt
object_log/__init__.py
object_log/models.py
object_log/urls.py
object_log/views.py
object_log/management/__init__.py
object_log/management/commands/__init__.py
object_log/management/commands/rebuild_log_cache.py
object_log/migrations/0001_version_0_5.py
object_log/migrations/0002_version_0_6.py
object_log/migrations/0003_version_0_6_rebuild_log_cache.py
object_log/migrations/__init__.py
object_log/muddle/__init__.py
object_log/muddle/mixers.py
object_log/templates/object_log/add.html
object_log/templates/object_log/delete.html
object_log/templates/object_log/edit.html
object_log/templates/object_log/log.html
object_log/templates/object_log/muddle/group_log_tab.html
object_log/templates/object_log/muddle/user_actions_tab.html
object_log/templates/object_log/muddle/user_log_tab.html
object_log/templatetags/__init__.py
object_log/templatetags/object_log_tags.py
object_log/tests/__init__.py
object_log/tests/logging.py