Metadata-Version: 1.0
Name: django-object-log
Version: 0.7
Summary: A method for logging user actions on models
Home-page: http://code.osuosl.org/projects/django-object-log
Author: Corbin Simpson
Author-email: simpsoco@osuosl.org
License: UNKNOWN
Platform: UNKNOWN
Classifier: License :: OSI Approved :: MIT License
Classifier: Framework :: Django
